ts_ids_components/__init__.py
ts_ids_components/chromatography/__init__.py
ts_ids_components/chromatography/method.py
ts_ids_components/chromatography/peak.py
ts_ids_components/chromatography/system.py
ts_ids_components/clonal_imager/__init__.py
ts_ids_components/liquid_handler.py
ts_ids_components/pcr/__init__.py
ts_ids_components/plate_reader/__init__.py
ts_ids_components/plate_reader/methods.py
ts_ids_components/py.typed
ts_ids_components/solvent_selection/__init__.py
ts_ids_components/spectrophotometry/__init__.py
ts_ids_components/tangential_flow_filtration/__init__.py
ts_ids_components-0.12.0.dist-info/METADATA
ts_ids_components-0.12.0.dist-info/WHEEL
ts_ids_components-0.12.0.dist-info/licenses/LICENSE
ts_ids_components-0.12.0.dist-info/RECORD
