Metadata-Version: 2.4
Name: ts-ids-components
Version: 0.12.0
Summary: A collection of domain specific IDS components
License: CC-BY-NC-ND-4.0
License-File: LICENSE
Author: TetraScience
Author-email: developers@tetrascience.com
Requires-Python: >=3.9,<4
Classifier: License :: Other/Proprietary License
Classifier: Programming Language :: Python :: 3
Classifier: Programming Language :: Python :: 3.9
Classifier: Programming Language :: Python :: 3.10
Classifier: Programming Language :: Python :: 3.11
Classifier: Programming Language :: Python :: 3.12
Classifier: Programming Language :: Python :: 3.13
Classifier: Programming Language :: Python :: 3.14
Requires-Dist: ts-ids-core (>=2.0.0,<3.0.0)
